CHANGELOG
LICENSE
LICENSE.txt
MANIFEST.in
README.md
WAIVER
WAIVER.asc
requirements.txt
setup.cfg
setup.py
test_requirements.txt
xml_requirements.txt
funga/error.py
funga/keystore.py
funga/signer.py
funga.egg-info/PKG-INFO
funga.egg-info/SOURCES.txt
funga.egg-info/dependency_links.txt
funga.egg-info/requires.txt
funga.egg-info/top_level.txt
funga/data/xmldsig-core-schema.xsd
funga/data/xmldsig1-schema.xsd
funga/data/xmldsig11-schema.xsd
tests/test_xml.py