Metadata-Version: 2.1
Name: funga
Version: 0.5.7
Summary: A signer and keystore daemon and library for cryptocurrency software development
Home-page: https://git.defalsify.org/funga
Author: Louis Holbrook
Author-email: dev@holbrook.no
License: AGPLv3+
Classifier: Programming Language :: Python :: 3
Classifier: Operating System :: OS Independent
Classifier: Development Status :: 4 - Beta
Classifier: Intended Audience :: Developers
Classifier: Topic :: Software Development :: Libraries
Classifier: License :: OSI Approved :: GNU Affero General Public License v3 or later (AGPLv3+)
Provides-Extra: xml
License-File: LICENSE
